Workbook
Name IBCmensualizado: Datos!$B$18
Name ListaCondicional: IF( AND('Certificación Mensual'!$C$41='Certificación Mensual'!$C$42, NOT(ISBLANK('Certificación Mensual'!$C$41)),NOT(ISBLANK('Certificación Mensual'!$C$42))),Datos!$K$2:$K$3,"NO" )
Name Pension: Datos!$B$7
Name Pensionado: 'Certificación Mensual'!$G$18
Name Porcentaje_IBC: Datos!$B$5
Name Salario_Minimo: Datos!$B$3
Name Salud: Datos!$B$6
Name UVT: Datos!$B$4
Name Vigencia: Datos!$B$2

Sheet Instrucciones
B1: INSTRUCCIONES DE DILIGENCIAMIENTO
B3: Este es un formato mediante el cual usted declara que pertenece a la cédula de Rentas de Trabajo establecida en el artículo103 del Estatuto Tributario, y que la información suministrada es fidedigna y corresponde a los soportes que permiten obtener las deducciones y rentas exentas para aplicar en los contratos de prestación de servicios suscritos con la Universidad Nacional de Colombia. La finalidad del formato es para efectos tributarios y de control.
B5: ¿EN QUÉ CASOS UNA PERSONA NATURAL PERTENECE A LA CÉDULA DE RENTAS DE TRABAJO? | C5: ¿EN QUÉ CASOS UNA PERSONA NATURAL NO PERTENECE A LA CÉDULA DE RENTAS DE TRABAJO?
B6: Se considera que una persona natural pertenece a la cédula de Rentas de Trabajo cuando: - Presta el servicio personalmente. - No tiene empleados ejecutando el contrato. - No existe una empresa o estructura empresarial detrás del servicio. - El ingreso depende directamente de su trabajo y conocimiento. - Declara anualmente sus ingresos como rentas de trabajo. | C6: Se considera que una persona natural no pertenece a la cédula de Rentas de Trabajo cuando: - Tiene personal contratado que ejecuta el servicio. - Existe venta o comercialización de equipos, materiales, insumos o mercancías en general. - Se realizan arreglos locativos que incluyen materiales. - El ingreso corresponde a una actividad comercial. - Declara el ingreso con costos y gastos asociados.
B8: 1. DATOS GENERALES
B9: Nombre del Contratista: | C9: Registre su nombre completo tal como aparece en su documento de identidad.
B10: Tipo y número de documento de identificación | C10: Indique el tipo de documento (CC, CE, etc.) y el número correspondiente.
B11: Correo institucional | C11: Registre el correo incluido el @unal.edu.co, si no tienen un correo institucional por favor dejar en blanco
B12: Fecha de diligenciamiento | C12: Indique la fecha en la que diligencia este formato.
B13: ¿Es usted pensionado ? | C13: Seleccione “SI" únicamente si aplica al menos una de estas condiciones: 1. Ya cuenta con pensión reconocida. 2. Cumple las semanas cotizadas exigidas para pensionarse. 3.Obtuvo devolución de saldos o indemnización sustitutiva, según corresponda.
B15: 2. RELACIÓN DE CONTRATOS QUE ORIGINAN PAGOS
B16: Empresa en QUIPU | C16: Corresponde al código de la empresa en la cual se encuentra registrada su orden contractual. Este dato lo puede obtener del Formato: Comunicación de legalización de orden contractual o contrato "Empresa (Código QUIPU)"
B17: Tipo Orden Contractual | C17: Indique el tipo de de la orden o contrato vigente.
B18: Número orden contractual | C18: Registre unicamente el número de la orden o contrato vigente.
B19: Valor total del contrato antes de IVA | C19: Indique el valor total del contrato sin incluir IVA.
B20: Fecha de inicio | C20: Registre la fecha de inicio del contrato en formato dd/mm/aaaa
B21: Fecha de terminación | C21: Registre la fecha de finalización del contrato en formato dd/mm/aaaa
B22: Clase de riesgos laborales | C22: Indique la clase de riesgo asignado el cual se puede verificar en el certificado de afiliación a la ARL
B24: 3. ANEXOS: DOCUMENTOS PARA SOPORTE DE DEDUCCIONES
B26: Esta sección aplica solo si desea solicitar deducciones y si sus ingresos mensualizados son superiores a 95 UVT. Marque y adjunte únicamente los documentos que apliquen a su caso. Si no adjunta los soportes correctos, no se aplicarán las deducciones. Las deducciones se aplicarán unicamente a un solo contrato.
B28: Solicito aplicar mis deducciones al contrato No. | C28: Seleccione de la lista desplegable la información del contrato al que solicita aplicar las deducciones. Este campo es obligatorio; la falta de diligenciamiento será causal de devolución.
B29: Formato de Certificado de dependientes | C29: Formato U.FT.12.010.077 Declaración para la deducción de pagos por dependientes (máximo 4) - con sus documentos anexos
B30: Certificado de intereses o corrección monetaria por préstamos para adquisición de vivienda | C30: Certificado expedido por la entidad financiera del año gravable anterior
B31: Certificado de cuentas de ahorro y pago de aporte mensual para el fomento de la construcción - AFC | C31: Certificado expedido por la entidad financiera donde constan los aportes realizados a una cuenta AFC en el año gravable anterior. Para hacer posible la deducción se debe anexar adicionalmente una autorización por parte del contratista que autorice la transferencia a la cuenta AFC por parte de la Universidad.
B32: Certificado de seguro de salud - Póliza | C32: Factura o certificación de la aseguradora, acompañada del comprobante de pago, correspondiente al período del pago
B33: Comprobante de pago mensual de Medicina Prepagada | C33: Factura y comprobante de pago emitidos por la entidad de medicina prepagada siempre que corresponda al mismo período del pago solicitado.
B34: Aportes voluntarios a pensión - AVP | C34: Certificado anual de Aportes Voluntarios a Pensión, expedido por el fondo de pensiones (público o privado) del año anterior. Para hacer posible la deducción se debe anexar adicionalmente una autorización por parte del contratista que autorice el pago de AVP por parte de la Universidad.
B36: Periodo de solicitud de pago | C36: Registre el periodo al cual corresponde la solicitud de pago. Debe estar en formato mm/yyyy Ejemplo: 05/2026
B37: Periodo de la planilla | C37: Indique el periodo de pago de la planilla de aportes al Sistema de Seguridad Social que adjunta como independiente. Debe estar en formato mm/yyyy. Ejemplo: 05/2026
B39: Declaración formal para disminución de base de retención | C39: Seleccione "SI" o "NO" segun corresponda. Seleccione “SI” únicamente si desea que se le aplique la disminución de la base de retención por los aportes al Sistema de Seguridad Social y siempre que el período de la solicitud de pago coincida con el período de la planilla efectivamente pagada. En caso contrario seleccion "NO".
B41: 4. CALCULO APORTES OBLIGATORIOS AL SISTEMA DE SEGURIDAD SOCIAL INTEGRAL (SGSSI) MENSUALES
B42: Esta sección calcula automaticamente los aportes obligatorios a salud, pensión, fondo de solidaridad y subsistencia (cuando aplica) y ARL (cuando aplica), con base en el Ingreso Base de Cotización (IBC) mensual.
B44: 5. MENSUALIZACIÓN CONTRACTUAL
B46: Esta sección determina automaticamente el valor mensual del contrato teniendo en cuenta el número de meses de ejecución del mismo, y el ingreso base de cotización (IBC) para el calculo de los aportes al sistema de seguridad social.
B48: 6. BASE DE RETENCIÓN MENSUALIZADA
B49: Esta sección calcula automaticamente la base sobre la cual se aplicará la retención en la fuente.
B51: 7. FIRMA DEL CONTRATISTA
B52: Cuando el trámite se realice a través de la Central de Pagos, no se requiere firma, dado que el diligenciamiento y envío de la información mediante el usuario y contraseña asignados constituye firma electrónica y representa la manifestación expresa de voluntad del contratista. Cuando el trámite no se realice por la Central de Pagos, el formato deberá ser firmado por el contratista para su validez.
B54: Una vez finalice el diligenciamiento, guarde o imprima el archivo en formato PDF únicamente de la hoja de Certificación Mensual y adjúntelo posteriormente a la solicitud de pago.

Sheet Certificación Mensual
B2: Proceso: Gestión Financiera
B3: Formato: Certificación determinación cedular Rentas de Trabajo
B4: Etapa: Ejecutar y reconocer los hechos económicos y financieros
B7: =CONCATENATE("Este formato aplica para la vigencia ", Vigencia) -> Este formato aplica para la vigencia 2026
B9: INFORMACIÓN DE LA PERSONA NATURAL
B10: DECLARACIÓN BAJO GRAVEDAD DE JURAMENTO
B11: =CONCATENATE("Yo, ",D17,Datos!A22,) -> Yo, identificado como aparece al pie de mi firma, declaro bajo gravedad de juramento, que pertenezco a la cédula de Rentas de Trabajo establecida en el artículo103 del Estatuto Tributario, y que la información suministrada es fidedigna y corresponde a los soportes que me permiten obtener las deducciones y rentas exentas para aplicar en los siguientes contratos de prestación de servicios suscritos con la Universidad Nacional de Colombia.
B13: NOTA: Favor diligenciar las celdas editables de color azul claro
B15: 1. DATOS GENERALES
B17: Nombre del Contratista | G17: Fecha de diligenciamiento
B18: Tipo y número de documento de identificación | G18: ¿Es usted pensionado ?
B19: Correo institucional
B21: 2. RELACIÓN DE CONTRATOS QUE ORIGINAN PAGOS (a)
B22: NOMBRE O RAZÓN SOCIAL DEL CONTRATANTE | C22: EMPRESA EN QUIPU | D22: TIPO ORDEN CONTRACTUAL | E22: NÚMERO ORDEN CONTRACTUAL | F22: VALOR TOTAL DEL CONTRATO ANTES DE IVA | G22: FECHA DE INICIO (DD/MM/AAAA) | H22: FECHA DE TERMINACION (DD/MM/AAAA) | I22: CLASE DE RIESGOS LABORALES (b)
B28: TOTAL | F28: =SUM(F23:F27) -> 0
B30: (a) Si tiene varias Ordenes Contractuales de Prestación de Servicios suscritas con la Universidad Nacional de Colombia y que se encuentren en ejecución dentro del periodo de solicitud de pago, debe relacionarlas una a una.
B31: (b) Seleccione el tipo de riesgos laborales de acuerdo al certificado de afiliación (Recuerde que cuando las ordenes establezcan diferentes tipos de riesgo, el aporte pago debe realizarse por el porcentaje mas alto).
B33: =+IF(B57=0,"",IF(B57<(UVT*95),"Debido a que sus ingresos mensuales son inferiores a 95 UVT NO debe presentar los documentos descritos en la seccion 3. ANEXOS para soportes de deducciones.","Debido a que sus ingresos mensuales son superiores a 95 UVT puede presentar los documentos descritos en la seccion 3. ANEXOS para soportes de deducciones."))
B35: 3. ANEXOS: DOCUMENTOS PARA SOPORTE DE DEDUCCIONES | G35: 4. CALCULO APORTES OBLIGATORIOS AL SISTEMA DE SEGURIDAD SOCIAL INTEGRAL (SGSSI) MENSUALES
B36: Solicito aplicar mis deducciones al contrato No. | G36: Aporte obligatorio a salud (12,5%) | I36: =+Datos!F16 -> 0
B37: Formato de Certificado de dependientes | C37: NO | D37: Certificado de seguro de salud - Póliza | E37: NO | G37: Aporte obligatorio a pensión (16%) | I37: =Datos!G16 -> 0
B38: Certificado de intereses o corrección monetaria por préstamos para adquisición de vivienda | C38: NO | D38: Comprobante de pago mensual de Medicina Prepagada | E38: NO | G38: Fondo de solidaridad pensional | I38: =Datos!H16 -> 0
B39: Certificado de cuentas de ahorro y pago de aporte mensual para el fomento de la construcción - AFC | C39: NO | D39: Aportes voluntarios a pensión | E39: NO | G39: Aportes a Riesgos laborales (ARL) | I39: =Datos!J16 -> 0
G40: Total Aportes Obligatorios | I40: =+SUM(I36:I39) -> 0
B41: Periodo de solicitud de pago
B42: Periodo de la planilla
B44: DECLARACIÓN FORMAL PARA DISMINUCIÓN DE BASE DE RETENCIÓN | G44: 7. FIRMA DEL CONTRATISTA
B45: Declaro bajo la gravedad de juramento, para efectos de verificación, control, trámite de pago y disminución de base de retención, y en cumplimiento de lo dispuesto en el parágrafo 1 del artículo 4 del Decreto 2271 de 2009, Artículo 126-1 del Estatuto Tributario y las demás normas que regulan el Sistema de Seguridad Social Integral, que los documentos que adjunto a la presente declaración corresponden al pago efectivo, oportuno y completo de los aportes obligatorios al Sistema de Seguridad Social Integral, por los conceptos de salud y pensión, asociados a la(s) orden(es) contractual(es) correspondiente(s) y al mismo período que origina el pago objeto de verificación. Así mismo, manifiesto expresamente que los ingresos correspondientes al período de cotización declarado se encuentran determinados conforme a lo previsto en el artículo 3 del Decreto 510 de 2003 y las normas concordantes, esto es, sobre el ingreso realmente percibido, dentro de los topes legales aplicables.
G47: Nombre: | H47: =IF(D17="","",D17)
G48: Número de documento de identificación | H48: =IF(D18="","",D18)
B50: 5. MENSUALIZACIÓN CONTRACTUAL | F50: 6. BASE DE RETENCIÓN MENSUALIZADA
B51: VALOR MENSUALIZADO | C51: NÚMERO DE MESES | D51: INGRESO BASE DE COTIZACIÓN POR CONTRATO IBC (40%). VR MENSUALIZADO | F51: APORTE OBLIGATORIO A SALUD (12,5) | G51: APORTE OBLIGATORIO A PENSIÓN (16%) | H51: FONDO DE SOLIDARIDAD PENSIONAL Y SUBSISTENCIA | I51: BASE DE RETENCIÓN MENSUAL
B52: =+IF(C52=0,0,F23/C52) -> 0 | C52: =+IF(OR(G23="",H23=""),0,((YEAR(H23)-YEAR(G23))*12)+MONTH(H23)-MONTH(G23)+1) -> 0 | D52: =+B52*Porcentaje_IBC -> 0 | F52: =IFERROR(+D52/SUM(Datos!$D$11:$D$15)*I$36,0) -> 0 | G52: =IFERROR(+D52/SUM(Datos!$D$11:$D$15)*$I$37,0) -> 0 | H52: =IFERROR(D52/SUM(Datos!$D$11:$D$15)*$I$38,0) -> 0 | I52: =IF($E$45=" SI ",B52-F52-G52-H52,B52) -> 0
B53: =+IF(C53=0,0,F24/C53) -> 0 | C53: =+IF(OR(G24="",H24=""),0,((YEAR(H24)-YEAR(G24))*12)+MONTH(H24)-MONTH(G24)+1) -> 0 | D53: =+B53*Porcentaje_IBC -> 0 | F53: =IFERROR(+D53/SUM(Datos!$D$11:$D$15)*I$36,0) -> 0 | G53: =IFERROR(+D53/SUM(Datos!$D$11:$D$15)*$I$37,0) -> 0 | H53: =IFERROR(D53/SUM(Datos!$D$11:$D$15)*$I$38,0) -> 0 | I53: =IF($E$45=" SI ",B53-F53-G53-H53,B53) -> 0
B54: =+IF(C54=0,0,F25/C54) -> 0 | C54: =+IF(OR(G25="",H25=""),0,((YEAR(H25)-YEAR(G25))*12)+MONTH(H25)-MONTH(G25)+1) -> 0 | D54: =+B54*Porcentaje_IBC -> 0 | F54: =IFERROR(+D54/SUM(Datos!$D$11:$D$15)*I$36,0) -> 0 | G54: =IFERROR(+D54/SUM(Datos!$D$11:$D$15)*$I$37,0) -> 0 | H54: =IFERROR(D54/SUM(Datos!$D$11:$D$15)*$I$38,0) -> 0 | I54: =IF($E$45=" SI ",B54-F54-G54-H54,B54) -> 0
B55: =+IF(C55=0,0,F26/C55) -> 0 | C55: =+IF(OR(G26="",H26=""),0,((YEAR(H26)-YEAR(G26))*12)+MONTH(H26)-MONTH(G26)+1) -> 0 | D55: =+B55*Porcentaje_IBC -> 0 | F55: =IFERROR(+D55/SUM(Datos!$D$11:$D$15)*I$36,0) -> 0 | G55: =IFERROR(+D55/SUM(Datos!$D$11:$D$15)*$I$37,0) -> 0 | H55: =IFERROR(D55/SUM(Datos!$D$11:$D$15)*$I$38,0) -> 0 | I55: =IF($E$45=" SI ",B55-F55-G55-H55,B55) -> 0
B56: =+IF(C56=0,0,F27/C56) -> 0 | C56: =+IF(OR(G27="",H27=""),0,((YEAR(H27)-YEAR(G27))*12)+MONTH(H27)-MONTH(G27)+1) -> 0 | D56: =+B56*Porcentaje_IBC -> 0 | F56: =IFERROR(+D56/SUM(Datos!$D$11:$D$15)*I$36,0) -> 0 | G56: =IFERROR(+D56/SUM(Datos!$D$11:$D$15)*$I$37,0) -> 0 | H56: =IFERROR(D56/SUM(Datos!$D$11:$D$15)*$I$38,0) -> 0 | I56: =IF($E$45=" SI ",B56-F56-G56-H56,B56) -> 0
B57: =SUM(B52:B56) -> 0 | D57: =IF(SUM(D52:D56)=0,0,Datos!D16) -> 0 | I57: =SUM(I52:I56) -> 0
B59: La Universidad Nacional de Colombia, como responsable del Tratamiento de Datos Personales, informa que los datos de carácter personal recolectados mediante este formato, se encuentran bajo medidas que garantizan la seguridad, confidencialidad e integridad y su tratamiento se realiza de acuerdo al cumplimiento normativo de la Ley 1581 de 2012 y de la Política de Tratamiento de Datos de la Universidad Nacional de Colombia. Puede ejercer sus derechos como titular a conocer, actualizar, rectificar y revocar las autorizaciones dadas a las finalidades aplicables a través de los canales dispuestos y disponibles en www.unal.edu.co o e-mail: protecdatos_na@unal.edu.co.
B60: Código: U.FT.12.010.069 | E60: Versión: 6.0 | I60: Página: 1 de 1

Sheet Datos
D1: Tarifas ARL | G1: Tarifas Fondo de Solidaridad Pensional y Subsistencia | K1: Lista Condicional
A2: Vigencia | B2: 2026 | D2: Clase Riesgo | E2: Tarifa | G2: Rango inferior | H2: Rango Superior | I2: Tarifa | K2: SI
A3: Salario Minimo | B3: 1750905 | D3: Riesgo 1 | E3: 0.00522 | G3: 4 | H3: 16 | I3: 0.01 | K3: NO
A4: UVT | B4: 52374 | D4: Riesgo 2 | E4: 0.01044 | G4: 16 | H4: 17 | I4: 0.012
A5: Porcentaje IBC | B5: 0.4 | D5: Riesgo 3 | E5: 0.02436 | G5: 17 | H5: 18 | I5: 0.014
A6: Salud | B6: 0.125 | D6: Riesgo 4 | E6: 0.0435 | G6: 18 | H6: 19 | I6: 0.016
A7: Pension | B7: 0.16 | D7: Riesgo 5 | E7: 0.0696 | G7: 19 | H7: 20 | I7: 0.018
G8: 20 | H8: 25 | I8: 0.02
A10: # | B10: Orden | C10: Valor Mensualizado | D10: IBC | E10: Salarios minimos | F10: Aportes Salud | G10: Aportes Pensión - | H10: Fondo de Solidaridad Pensional y subsistencia | I10: Clase ARL | J10: ARL
A11: 1 | B11: =IF(ISBLANK('Certificación Mensual'!E23),"",CONCATENATE('Certificación Mensual'!C23,"-",'Certificación Mensual'!D23,"-",'Certificación Mensual'!E23,"-",YEAR('Certificación Mensual'!G23) )) | C11: ='Certificación Mensual'!B52 -> 0 | D11: =C11*$B$5 -> 0 | E11: =D11/$B$3 -> 0 | F11: =D11*$B$6 -> 0 | G11: =IF('Certificación Mensual'!I18="SI","0",D11*$B$7) -> 0 | H11: =+IF(AND(E11>=$G$3,E11<$H$3),D11*$I$3,IF(AND(E11>=$G$4,E11<$H$4),D11*$I$4,IF(AND(E11>=$G$5,E11<$H$5),D11*$I$5,IF(AND(E11>=$G$6,E11<$H$6),D11*$I$6,IF(AND(E11>=$G$7,E11<$H$7),D11*$I$7,IF(E11>=$G$8,D11*$I$8,IF(E11>=$H$8,Salario_Minimo*25*$I$8,0))))))) -> 0 | I11: {=IF(ISBLANK('Certificación Mensual'!H22ESPACIOS),"0",'Certificación Mensual'!I23)} -> 0 | J11: =IF(OR(I11="Riesgo 4",I11="Riesgo 5"),0,IFERROR(D11*INDEX($E$3:$E$7,MATCH(I11,$D$3:$D$7,0)),0)) -> 0
A12: 2 | B12: =IF(ISBLANK('Certificación Mensual'!E24),"",CONCATENATE('Certificación Mensual'!C24,"-",'Certificación Mensual'!D24,"-",'Certificación Mensual'!E24,"-",YEAR('Certificación Mensual'!G24) )) | C12: ='Certificación Mensual'!B53 -> 0 | D12: =C12*$B$5 -> 0 | E12: =D12/$B$3 -> 0 | F12: =D12*$B$6 -> 0 | G12: =IF('Certificación Mensual'!I20="SI","0",D12*$B$7) -> 0 | H12: =+IF(AND(E12>=$G$3,E12<$H$3),D12*$I$3,IF(AND(E12>=$G$4,E12<$H$4),D12*$I$4,IF(AND(E12>=$G$5,E12<$H$5),D12*$I$5,IF(AND(E12>=$G$6,E12<$H$6),D12*$I$6,IF(AND(E12>=$G$7,E12<$H$7),D12*$I$7,IF(E12>=$G$8,D12*$I$8,IF(E12>=$H$8,Salario_Minimo*25*$I$8,0))))))) -> 0 | I12: {=IF(ISBLANK('Certificación Mensual'!H22ESPACIOS),"0",'Certificación Mensual'!I24)} -> 0 | J12: =IF(OR(I12="Riesgo 4",I12="Riesgo 5"),0,IFERROR(D12*INDEX($E$3:$E$7,MATCH(I12,$D$3:$D$7,0)),0)) -> 0
A13: 3 | B13: =IF(ISBLANK('Certificación Mensual'!E25),"",CONCATENATE('Certificación Mensual'!C25,"-",'Certificación Mensual'!D25,"-",'Certificación Mensual'!E25,"-",YEAR('Certificación Mensual'!G25) )) | C13: ='Certificación Mensual'!B54 -> 0 | D13: =C13*$B$5 -> 0 | E13: =D13/$B$3 -> 0 | F13: =D13*$B$6 -> 0 | G13: =IF('Certificación Mensual'!I21="SI","0",D13*$B$7) -> 0 | H13: =+IF(AND(E13>=$G$3,E13<$H$3),D13*$I$3,IF(AND(E13>=$G$4,E13<$H$4),D13*$I$4,IF(AND(E13>=$G$5,E13<$H$5),D13*$I$5,IF(AND(E13>=$G$6,E13<$H$6),D13*$I$6,IF(AND(E13>=$G$7,E13<$H$7),D13*$I$7,IF(E13>=$G$8,D13*$I$8,IF(E13>=$H$8,Salario_Minimo*25*$I$8,0))))))) -> 0 | I13: {=IF(ISBLANK('Certificación Mensual'!H22ESPACIOS),"0",'Certificación Mensual'!I25)} -> 0 | J13: =IF(OR(I13="Riesgo 4",I13="Riesgo 5"),0,IFERROR(D13*INDEX($E$3:$E$7,MATCH(I13,$D$3:$D$7,0)),0)) -> 0
A14: 4 | B14: =IF(ISBLANK('Certificación Mensual'!E26),"",CONCATENATE('Certificación Mensual'!C26,"-",'Certificación Mensual'!D26,"-",'Certificación Mensual'!E26,"-",YEAR('Certificación Mensual'!G26) )) | C14: ='Certificación Mensual'!B55 -> 0 | D14: =C14*$B$5 -> 0 | E14: =D14/$B$3 -> 0 | F14: =D14*$B$6 -> 0 | G14: =IF('Certificación Mensual'!I22="SI","0",D14*$B$7) -> 0 | H14: =+IF(AND(E14>=$G$3,E14<$H$3),D14*$I$3,IF(AND(E14>=$G$4,E14<$H$4),D14*$I$4,IF(AND(E14>=$G$5,E14<$H$5),D14*$I$5,IF(AND(E14>=$G$6,E14<$H$6),D14*$I$6,IF(AND(E14>=$G$7,E14<$H$7),D14*$I$7,IF(E14>=$G$8,D14*$I$8,IF(E14>=$H$8,Salario_Minimo*25*$I$8,0))))))) -> 0 | I14: {=IF(ISBLANK('Certificación Mensual'!H22ESPACIOS),"0",'Certificación Mensual'!I26)} -> 0 | J14: =IF(OR(I14="Riesgo 4",I14="Riesgo 5"),0,IFERROR(D14*INDEX($E$3:$E$7,MATCH(I14,$D$3:$D$7,0)),0)) -> 0
A15: 5 | B15: =IF(ISBLANK('Certificación Mensual'!E27),"",CONCATENATE('Certificación Mensual'!C27,"-",'Certificación Mensual'!D27,"-",'Certificación Mensual'!E27,"-",YEAR('Certificación Mensual'!G27) )) | C15: ='Certificación Mensual'!B56 -> 0 | D15: =C15*$B$5 -> 0 | E15: =D15/$B$3 -> 0 | F15: =D15*$B$6 -> 0 | G15: =IF('Certificación Mensual'!I23="SI","0",D15*$B$7) -> 0 | H15: =+IF(AND(E15>=$G$3,E15<$H$3),D15*$I$3,IF(AND(E15>=$G$4,E15<$H$4),D15*$I$4,IF(AND(E15>=$G$5,E15<$H$5),D15*$I$5,IF(AND(E15>=$G$6,E15<$H$6),D15*$I$6,IF(AND(E15>=$G$7,E15<$H$7),D15*$I$7,IF(E15>=$G$8,D15*$I$8,IF(E15>=$H$8,Salario_Minimo*25*$I$8,0))))))) -> 0 | I15: {=IF(ISBLANK('Certificación Mensual'!H22ESPACIOS),"0",'Certificación Mensual'!I27)} -> 0 | J15: =IF(OR(I15="Riesgo 4",I15="Riesgo 5"),0,IFERROR(D15*INDEX($E$3:$E$7,MATCH(I15,$D$3:$D$7,0)),0)) -> 0
C16: =IF(SUM(C11:C15)<Salario_Minimo,Salario_Minimo,SUM(C11:C15)) -> 1750905 | D16: =IF(SUM(D11:D15)=0,0,MAX(Salario_Minimo,MIN(SUM(D11:D15),25*Salario_Minimo))) -> 0 | E16: =SUM(E11:E15) -> 0 | F16: =IF(SUM(F11:F15)=0,0,MROUND(IF(SUM(F11:F15)<Salario_Minimo*Salud,Salario_Minimo*Salud,IF(SUM(F11:F15)>Salario_Minimo*Salud*25,Salario_Minimo*Salud*25,(SUM(F11:F15)))),100)) -> 0 | G16: =IF(SUM(G11:G15)=0,0,MROUND(IF('Certificación Mensual'!I18="SI","0",IF(SUM(G11:G15)<Salario_Minimo*Pension,Salario_Minimo*Pension,IF(SUM(G11:G15)>Salario_Minimo*Pension*25,Salario_Minimo*Pension*25,SUM(G11:G15)))),100)) -> 0 | H16: =MROUND(IF(AND(E16>=$G$3,E16<$H$3),D16*$I$3,IF(AND(E16>=$G$4,E16<$H$4),D16*$I$4,IF(AND(E16>=$G$5,E16<$H$5),D16*$I$5,IF(AND(E16>=$G$6,E16<$H$6),D16*$I$6,IF(AND(E16>=$G$7,E16<$H$7),D16*$I$7,IF(E16>=$G$8,D16*$I$8,IF(E16>=$H$8,Salario_Minimo*25*$I$8,0))))))),100) -> 0 | J16: {=MROUND(IFERROR(IF(MAX(IF((VALUE(RIGHT($I$11:$I$15,1))>=1)*(VALUE(RIGHT($I$11:$I$15,1))<=3),VALUE(RIGHT($I$11:$I$15,1)),0))=0,0,D16*INDEX($E$3:$E$7,MATCH("Riesgo "&MAX(IF((VALUE(RIGHT($I$11:$I$15,1))>=1)*(VALUE(RIGHT($I$11:$I$15,1))<=3),VALUE(RIGHT($I$11:$I$15,1)),0)),$D$3:$D$7,0))),0),100)} -> 0
A18: Ingreso mensualizado | B18: =ROUND(C16,0) -> 1750905 | H18: =+IF(AND(E11>=$G$3,E11<$H$3),D11*$I$3,IF(AND(E11>=$G$4,E11<$H$4),D11*$I$4,IF(AND(E11>=$G$5,E11<$H$5),D11*$I$5,IF(AND(E11>=$G$6,E11<$H$6),D11*$I$6,IF(AND(E11>=$G$7,E11<$H$7),D11*$I$7,IF(E11>=$G$8,D11*$I$8,IF(E11>=$H$8,Salario_Minimo*25*$I$8,0))))))) -> 0
A19: Valor ingreso en UVT | B19: =C16/UVT -> 33.430805
A22: identificado como aparece al pie de mi firma, declaro bajo gravedad de juramento, que pertenezco a la cédula de Rentas de Trabajo establecida en el artículo103 del Estatuto Tributario, y que la información suministrada es fidedigna y corresponde a los soportes que me permiten obtener las deducciones y rentas exentas para aplicar en los siguientes contratos de prestación de servicios suscritos con la Universidad Nacional de Colombia.
G45: 656600
